setup.py
pynxos/__init__.py
pynxos/device.py
pynxos/errors.py
pynxos.egg-info/PKG-INFO
pynxos.egg-info/SOURCES.txt
pynxos.egg-info/dependency_links.txt
pynxos.egg-info/requires.txt
pynxos.egg-info/top_level.txt
pynxos/features/__init__.py
pynxos/features/base_feature.py
pynxos/features/file_copy.py
pynxos/features/vlans.py
pynxos/lib/__init__.py
pynxos/lib/rpc_client.py
pynxos/lib/data_model/__init__.py
pynxos/lib/data_model/converters.py
pynxos/lib/data_model/key_maps.py
pynxos/lib/data_model/schemas/__init__.py